{
  "race_id": "2026-04-12_ST_R11",
  "date": "2026-04-12T00:00:00",
  "race_number": 11,
  "distance": 1200,
  "track_type": "Turf",
  "course": "A",
  "race_class": "Class 2",
  "track_condition": "Good",
  "predicted_pace": "EVEN",
  "jump_time": "17:45\n",
  "horses": [
    {
      "horse_id": "N/A",
      "horse_name": "COLOURFUL KING",
      "owner": "",
      "sire": null,
      "dam": null,
      "saddle_number": 1,
      "draw": 12,
      "jockey": "Z Purton",
      "trainer": "D Eustace",
      "weight": 135.0,
      "optimal_weight_range": null,
      "training_location": "HK",
      "last_6_runs": [
        "6",
        "2",
        "2",
        "1",
        "2",
        "2"
      ],
      "gear": "",
      "stable_change": false,
      "trial_comments": null,
      "synergy_score": 0.0
    },
    {
      "horse_id": "N/A",
      "horse_name": "SKY TRUST",
      "owner": "",
      "sire": null,
      "dam": null,
      "saddle_number": 2,
      "draw": 9,
      "jockey": "J Moreira",
      "trainer": "C Fownes",
      "weight": 133.0,
      "optimal_weight_range": null,
      "training_location": "HK",
      "last_6_runs": [
        "8",
        "2",
        "1",
        "7",
        "4",
        "1"
      ],
      "gear": "",
      "stable_change": false,
      "trial_comments": null,
      "synergy_score": 0.0
    },
    {
      "horse_id": "N/A",
      "horse_name": "GORGEOUS WIN",
      "owner": "",
      "sire": null,
      "dam": null,
      "saddle_number": 3,
      "draw": 11,
      "jockey": "J Orman",
      "trainer": "C S Shum",
      "weight": 130.0,
      "optimal_weight_range": null,
      "training_location": "HK",
      "last_6_runs": [
        "8",
        "9",
        "2",
        "11",
        "1",
        "10"
      ],
      "gear": "",
      "stable_change": false,
      "trial_comments": null,
      "synergy_score": 0.0
    },
    {
      "horse_id": "N/A",
      "horse_name": "SELF IMPROVEMENT",
      "owner": "",
      "sire": null,
      "dam": null,
      "saddle_number": 4,
      "draw": 2,
      "jockey": "P N Wong",
      "trainer": "K L Man",
      "weight": 130.0,
      "optimal_weight_range": null,
      "training_location": "HK",
      "last_6_runs": [
        "11",
        "8",
        "9",
        "1",
        "11",
        "4"
      ],
      "gear": "",
      "stable_change": false,
      "trial_comments": null,
      "synergy_score": 0.0
    },
    {
      "horse_id": "N/A",
      "horse_name": "CRIMSON FLASH",
      "owner": "",
      "sire": null,
      "dam": null,
      "saddle_number": 5,
      "draw": 3,
      "jockey": "A Atzeni",
      "trainer": "M Newnham",
      "weight": 127.0,
      "optimal_weight_range": null,
      "training_location": "HK",
      "last_6_runs": [
        "1",
        "11",
        "7",
        "5",
        "2",
        "1"
      ],
      "gear": "",
      "stable_change": false,
      "trial_comments": null,
      "synergy_score": 0.0
    },
    {
      "horse_id": "N/A",
      "horse_name": "MAGIC CONTROL",
      "owner": "",
      "sire": null,
      "dam": null,
      "saddle_number": 6,
      "draw": 10,
      "jockey": "K C Leung",
      "trainer": "W K Mo",
      "weight": 126.0,
      "optimal_weight_range": null,
      "training_location": "HK",
      "last_6_runs": [
        "9",
        "5",
        "5",
        "10",
        "5",
        "2"
      ],
      "gear": "",
      "stable_change": false,
      "trial_comments": null,
      "synergy_score": 0.0
    },
    {
      "horse_id": "N/A",
      "horse_name": "YOUNG CHAMPION",
      "owner": "",
      "sire": null,
      "dam": null,
      "saddle_number": 7,
      "draw": 7,
      "jockey": "H Bowman",
      "trainer": "J Size",
      "weight": 126.0,
      "optimal_weight_range": null,
      "training_location": "HK",
      "last_6_runs": [
        "1",
        "3",
        "2",
        "2",
        "11",
        "10"
      ],
      "gear": "",
      "stable_change": false,
      "trial_comments": null,
      "synergy_score": 0.0
    },
    {
      "horse_id": "N/A",
      "horse_name": "VICTOR THE WINNER",
      "owner": "",
      "sire": null,
      "dam": null,
      "saddle_number": 8,
      "draw": 4,
      "jockey": "M L Yeung",
      "trainer": "P C Ng",
      "weight": 122.0,
      "optimal_weight_range": null,
      "training_location": "HK",
      "last_6_runs": [
        "10",
        "11",
        "9",
        "8",
        "10",
        "14"
      ],
      "gear": "",
      "stable_change": false,
      "trial_comments": null,
      "synergy_score": 0.0
    },
    {
      "horse_id": "N/A",
      "horse_name": "RISING FORCE",
      "owner": "",
      "sire": null,
      "dam": null,
      "saddle_number": 9,
      "draw": 8,
      "jockey": "R Kingscote",
      "trainer": "P F Yiu",
      "weight": 117.0,
      "optimal_weight_range": null,
      "training_location": "HK",
      "last_6_runs": [
        "1",
        "2",
        "2",
        "1",
        "7",
        "2"
      ],
      "gear": "",
      "stable_change": false,
      "trial_comments": null,
      "synergy_score": 0.0
    },
    {
      "horse_id": "N/A",
      "horse_name": "CHATEAUNEUF",
      "owner": "",
      "sire": null,
      "dam": null,
      "saddle_number": 10,
      "draw": 6,
      "jockey": "L Hewitson",
      "trainer": "D A Hayes",
      "weight": 116.0,
      "optimal_weight_range": null,
      "training_location": "HK",
      "last_6_runs": [
        "6",
        "7",
        "11",
        "11",
        "5",
        "1"
      ],
      "gear": "",
      "stable_change": false,
      "trial_comments": null,
      "synergy_score": 0.0
    },
    {
      "horse_id": "N/A",
      "horse_name": "GALACTIC VOYAGE",
      "owner": "",
      "sire": null,
      "dam": null,
      "saddle_number": 11,
      "draw": 5,
      "jockey": "A Badel",
      "trainer": "K W Lui",
      "weight": 116.0,
      "optimal_weight_range": null,
      "training_location": "HK",
      "last_6_runs": [
        "5",
        "1",
        "1",
        "3",
        "4"
      ],
      "gear": "",
      "stable_change": false,
      "trial_comments": null,
      "synergy_score": 0.0
    },
    {
      "horse_id": "N/A",
      "horse_name": "PAKISTAN LEGACY",
      "owner": "",
      "sire": null,
      "dam": null,
      "saddle_number": 12,
      "draw": 1,
      "jockey": "K Teetan",
      "trainer": "W Y So",
      "weight": 116.0,
      "optimal_weight_range": null,
      "training_location": "HK",
      "last_6_runs": [
        "2",
        "1",
        "2",
        "7",
        "12",
        "6"
      ],
      "gear": "",
      "stable_change": false,
      "trial_comments": null,
      "synergy_score": 0.0
    }
  ]
}